setup.py
bugcrowd/__init__.py
bugcrowd/bugcrowd.py
bugcrowd.egg-info/PKG-INFO
bugcrowd.egg-info/SOURCES.txt
bugcrowd.egg-info/dependency_links.txt
bugcrowd.egg-info/not-zip-safe
bugcrowd.egg-info/requires.txt
bugcrowd.egg-info/top_level.txt