Metadata-Version: 1.1
Name: bugcrowd
Version: 0.1
Summary: Python wrapper for the Bugcrowd API
Home-page: https://github.com/leifdreizler/bugcrowd
Author: Leif Dreizler
Author-email: leifdreizler@gmail.com
License: MIT
Download-URL: https://github.com/leifdreizler/bugcrowd/archive/0.1.tar.gz
Keywords: bugcrowd
Platform: UNKNOWN
